netcloud/analyse/Analyse.py
netcloud/analyse/__init__.py
netcloud/crawler/Crawler.py
netcloud/crawler/__init__.py
netcloud/demo/SimpleAnalyseDemo.py
netcloud/demo/SimpleCrawlerDemo.py
netcloud/demo/SimpleLoginDemo.py
netcloud/demo/__init__.py
netcloud/login/Login.py
netcloud/login/Printer.py
netcloud/login/__init__.py
netcloud/test/NetCloudAnalyseTest.py
netcloud/test/NetCloudCrawlerTest.py
netcloud/test/NetCloudLoginTest.py
netcloud/test/__init__.py
netcloud/util/Constants.py
netcloud/util/Helper.py
netcloud/util/__init__.py
netcloud/util/source/JayChou.jpg
netcloud/util/source/city_coordinates.json
netcloud/util/source/config.template.xml
netcloud/util/source/province_cities.json
netcloud/util/source/simsun.ttc
netcloud/util/source/stopwords.txt
NetCloud-1.0.3.dist-info/METADATA
NetCloud-1.0.3.dist-info/WHEEL
NetCloud-1.0.3.dist-info/top_level.txt
NetCloud-1.0.3.dist-info/RECORD
