Metadata-Version: 2.1
Name: NetCloud
Version: 1.0.3
Summary: 网易云音乐综合爬虫,可以实现:
Home-page: http://www.github.com/Lyrichu/NetCloud
Author: lyrichu
Author-email: lyrichu@foxmail.com
Maintainer: lyrichu
Maintainer-email: lyrichu@foxmail.com
License: UNKNOWN
Platform: UNKNOWN
Requires-Dist: pycrypto
Requires-Dist: requests
Requires-Dist: pyecharts
Requires-Dist: pandas
Requires-Dist: jieba
Requires-Dist: wordcloud
Requires-Dist: scipy
